reg/__init__.py
reg/arginfo.py
reg/cache.py
reg/context.py
reg/dispatch.py
reg/error.py
reg/predicate.py
reg/tests/__init__.py
reg/tests/test_arginfo.py
reg/tests/test_classdispatch.py
reg/tests/test_dispatch.py
reg/tests/test_dispatch_method.py
reg/tests/test_docgen.py
reg/tests/test_predicate.py
reg/tests/test_registry.py
reg/tests/fixtures/__init__.py
reg/tests/fixtures/module.py
reg-0.12.dist-info/LICENSE.txt
reg-0.12.dist-info/METADATA
reg-0.12.dist-info/WHEEL
reg-0.12.dist-info/top_level.txt
reg-0.12.dist-info/RECORD
