Metadata-Version: 2.1
Name: reg
Version: 0.12
Summary: Clever dispatch
Home-page: http://reg.readthedocs.io
Author: Martijn Faassen
Author-email: faassen@startifact.com
License: BSD
Platform: UNKNOWN
Classifier: Intended Audience :: Developers
Classifier: License :: OSI Approved :: BSD License
Classifier: Topic :: Software Development :: Libraries :: Python Modules
Classifier: Programming Language :: Python :: 3.4
Classifier: Programming Language :: Python :: 3.5
Classifier: Programming Language :: Python :: 3.6
Classifier: Programming Language :: Python :: 3.7
Classifier: Programming Language :: Python :: 3.8
Classifier: Programming Language :: Python :: Implementation :: PyPy
Classifier: Development Status :: 5 - Production/Stable
Provides-Extra: test
Provides-Extra: pep8
Provides-Extra: coverage
Provides-Extra: docs
